{
    "name": "moira",
    "background": "utilitarian",
    "status": "normal",
    "location": "dining car",
    "inventory": [],
    "joy": 0,
    "trust": 0,
    "fear": 0,
    "surprise": 0,
    "sadness": 0,
    "disgust": 0,
    "anger": 0,
    "anticipation": 0,
    "clues": [
    ],
    "mysteries": {
        "Where am I?": {
            "current progress": "in progress",
            "unlocked theories": [
            ],
            "hunch": "none"
        }
    },
    "worldstate": {
        "dining car": "dark"
    },
    "history": {
    }
}